ym_csv_pii_sanitizer/__init__.py
ym_csv_pii_sanitizer/main.py
ym_csv_pii_sanitizer/test_main.py
ym_csv_pii_sanitizer-0.0.3.dist-info/METADATA
ym_csv_pii_sanitizer-0.0.3.dist-info/WHEEL
ym_csv_pii_sanitizer-0.0.3.dist-info/entry_points.txt
ym_csv_pii_sanitizer-0.0.3.dist-info/top_level.txt
ym_csv_pii_sanitizer-0.0.3.dist-info/RECORD
