Metadata-Version: 2.1
Name: ym-csv-pii-sanitizer
Version: 0.0.3
Summary: Redact a PHI (personal health
Author: Alex Ilin
Author-email: alex.ilin@ymeadows.com
Classifier: Programming Language :: Python :: 3
Requires-Dist: typer
Requires-Dist: presidio-analyzer
Requires-Dist: presidio-anonymizer
Requires-Dist: transformers
Requires-Dist: torch
